{"QawFAb67KFbZZo+hE4mhkQ==":"9-229x229.png","OSndt2g4HxHfrUbW3I5pVg==":"photo_2019-10-09_21-04-3-1280x719.jpg","ry/znsX1kFw2qAAixQWbtw==":"mbr-1920x1280.jpg","x+N8qd80OC/v0EbImp38HQ==":"mbr-1-1920x1280.jpg","MSEbhjZij5FrQ66FidDSOQ==":"mbr-2-1920x1280.jpg","nCunewN8AKQCjpJIy2kJFQ==":"mbr-1920x1126.jpg","VtUwTdoer/xRzhP5GBj/6A==":"mbr-1920x1285.jpg","mU5cju0lyhfkR7xC85t9NQ==":"mbr-3-1920x1280.jpg","yBQGbMqyf4uppHkUFcgQBQ==":"mbr-4-1920x1280.jpg","q6Xhs3gSP3Jtrxpq+64Gzw==":"ltw%20pitch%20(3)-2000x1125.jpeg","OGo9robFum+pqhn+mijYag==":"ltw%20pitch%20(3)-2000x1125.jpeg","erAIIG1q5ydNPg5xrme35Q==":"ltw%20pitch%20(3)-2000x1125.jpg","jvDgUQuHyVw1HeOY7MOX8Q==":"mbr-696x426.jpg","PzjwtHecC/UY9+j6K7vRBA==":"mbr-1-696x492.png","A4vgI6uYF6y2sgvNGRpQkQ==":"mbr-696x464.jpg","0oSldVMlEG5ldGb/NRItKg==":"collage-1275x707.jpg","eJfO4MES8ch/YJAgjzSP1g==":"collage-1275x707.jpeg","ctZZQJWgTenM46voWDTWOA==":"collage-1-1275x707.jpeg","WSTq4bnV/7ekDBPoK2ZTPw==":"mbr-1-696x464.jpg","QlVQi5m4YOig9PthroTTkA==":"adobestock-297372329-696x291.jpg","FJGUuuu6SV1lH8CAjQwXww==":"adobestock-213899225-696x464.jpg","/6hqKAIYfGsnAKeCpC7o/g==":"photo_2019-10-09_21-04-6-696x1239.jpg","GJ6wUAS8sJFe1kzwXfUgRg==":"photo_2019-10-09_21-04-6-696x1239.jpeg","DIvO1shib7vVAwxM2zE/wA==":"georgene-1138x640.jpg","ZcnVnUOlPoc7DSFTs677Qg==":"ltw%20deb-1280x960.jpg","te7t5912JfviO87qKKXU0A==":"nate-854x640.jpeg","JBkj/pKI93nrQRnmVqnzKw==":"ltw-1280x960.jpg","0lJcHHd8Rqg1jXD7h/iX1w==":"nate-1-854x640.jpeg","gyngqOwAsqftGLRsXtlkng==":"ltw%20jim-1280x720.jpg","PV9sK2U+Pe4wA64t8REm9A==":"nate-2-854x640.jpeg","wzW1RwskYgfcS7Sq5imLIg==":"photo_2019-10-09_21-04-4-719x1280.jpeg","kEWjdayxibcehzwLKcBujA==":"photo_2019-10-09_21-03-57-1280x720.jpeg","Ljna+6I4bS5Ax6Tq+/fWfw==":"ltw%20class%201-1280x960.jpg","ztPTYCFHTaN230gcbEfBuw==":"ltw%20class%201-1280x960.jpeg","ABH6LuKjLRseFjuW925GsA==":"ltw%20stage-720x1280.jpeg","vzL7dfr65/sZMPD9ORn5kg==":"joey-800x568.jpeg","n8rDjSh0BjwZsCKBJGHWsg==":"joey-1-800x568.jpeg","lfqDRrCTm4pC2Z0mj2E5gQ==":"matt%202-1280x960.jpg","YSkeT6f8lriMyBSiJLK/gQ==":"nate%20dog-1280x960.jpg","1dy1byBoHiaO3dpCKLuKTw==":"ltw%20stage-720x1280.jpeg","sBbWOQ1FsntX6FqQJhV9HA==":"miaata-803x546.jpg"}